MANIFEST.in
README.md
setup.py
uidgenerator/__init__.py
uidgenerator/admin.py
uidgenerator/apps.py
uidgenerator/models.py
uidgenerator/settings.py
uidgenerator/tests.py
uidgenerator/views.py
uidgenerator_utils.egg-info/PKG-INFO
uidgenerator_utils.egg-info/SOURCES.txt
uidgenerator_utils.egg-info/dependency_links.txt
uidgenerator_utils.egg-info/top_level.txt