Metadata-Version: 1.1
Name: uidgenerator-utils
Version: 0.4.1
Summary: A Django app to generate model id based on a snowflake of twitter.
Home-page: https://github.com/sugar2015/uidgenerator_utils
Author: wim
Author-email: wim114@dingtalk.com
License: UNKNOWN
Platform: UNKNOWN
Classifier: Environment :: Web Environment
Classifier: Framework :: Django
Classifier: Programming Language :: Python :: 3.6
